verilog/OR3/OR3.v
module OR3(input A, input B, input C, output Y);
    assign Y = A | B | C;
endmodule

verilog/OR3/tb_OR3.v
`timescale 1ns/1ps
module tb_OR3;
    reg A, B, C;
    wire Y;
    integer i;

    OR3 uut(.A(A), .B(B), .C(C), .Y(Y));

    initial begin
        $dumpfile("or3.vcd");
        $dumpvars(0, tb_OR3);

        for (i = 0; i < 8; i = i + 1) begin
            {A, B, C} = i;
            #10;
        end

        #20 $finish;
    end
endmodule

verilog/OR3/or3.vcd
$date
	Wed Dec  3 17:14:29 2025
$end
$version
	Icarus Verilog
$end
$timescale
	1ps
$end
$scope module tb_OR3 $end
$var wire 1 ! Y $end
$var reg 1 " A $end
$var reg 1 # B $end
$var reg 1 $ C $end
$var integer 32 % i [31:0] $end
$scope module uut $end
$var wire 1 " A $end
$var wire 1 # B $end
$var wire 1 $ C $end
$var wire 1 ! Y $end
$upscope $end
$upscope $end
$enddefinitions $end
$comment Show the parameter values. $end
$dumpall
$end
#0
$dumpvars
b0 %
0$
0#
0"
0!
$end
#10000
1!
1$
b1 %
#20000
1!
1#
0$
b10 %
#30000
1$
b11 %
#40000
1"
0#
0$
b100 %
#50000
1$
b101 %
#60000
1#
0$
b110 %
#70000
1$
b111 %
#80000
b1000 %
