verilog/AND4/AND4.v
module AND4(input A, input B, input C, input D, output Y);
    assign Y = A & B & C & D;
endmodule

verilog/AND4/tb_AND4.v
`timescale 1ns/1ps
module tb_AND4;
    reg A, B, C, D;
    wire Y;
    integer i;

    AND4 uut(.A(A), .B(B), .C(C), .D(D), .Y(Y));

    initial begin
        $dumpfile("and4.vcd");
        $dumpvars(0, tb_AND4);

        for (i = 0; i < 16; i = i + 1) begin
            {A, B, C, D} = i;
            #10;
        end

        #20 $finish;
    end
endmodule

verilog/AND4/and4.vcd
$date
	Wed Dec  3 17:15:02 2025
$end
$version
	Icarus Verilog
$end
$timescale
	1ps
$end
$scope module tb_AND4 $end
$var wire 1 ! Y $end
$var reg 1 " A $end
$var reg 1 # B $end
$var reg 1 $ C $end
$var reg 1 % D $end
$var integer 32 & i [31:0] $end
$scope module uut $end
$var wire 1 " A $end
$var wire 1 # B $end
$var wire 1 $ C $end
$var wire 1 % D $end
$var wire 1 ! Y $end
$upscope $end
$upscope $end
$enddefinitions $end
$comment Show the parameter values. $end
$dumpall
$end
#0
$dumpvars
b0 &
0%
0$
0#
0"
0!
$end
#10000
1%
b1 &
#20000
1$
0%
b10 &
#30000
1%
b11 &
#40000
1#
0$
0%
b100 &
#50000
1%
b101 &
#60000
1$
0%
b110 &
#70000
1%
b111 &
#80000
1"
0#
0$
0%
b1000 &
#90000
1%
b1001 &
#100000
1$
0%
b1010 &
#110000
1%
b1011 &
#120000
1#
0$
0%
b1100 &
#130000
1%
b1101 &
#140000
1$
0%
b1110 &
#150000
1!
1%
b1111 &
#160000
b10000 &
