verilog/NAND2/NAND2.v
module NAND2(input A, input B, output Y);
    assign Y = ~(A & B);
endmodule

verilog/master_slave_D_FF/master_slave_D_FF.v
// Master-Slave D flip-flop implemented using NAND2 gates
// Positive-edge triggered: master enabled when CLK=0 (nCLK=1), slave enabled when CLK=1
module master_slave_D_FF(
    input D,
    input CLK,
    output Q,
    output QN
);
    wire nD;   // ~D
    wire nCLK; // ~CLK

    // invert D and CLK using NAND as inverter
    wire n1, n2;
    NAND2 invD (.A(D), .B(D), .Y(nD));
    NAND2 invCLK(.A(CLK), .B(CLK), .Y(nCLK));

    // Master latch inputs (enabled when nCLK = 1 i.e., CLK=0)
    wire S_m, R_m;
    NAND2 mS (.A(D), .B(nCLK), .Y(S_m));
    NAND2 mR (.A(nD), .B(nCLK), .Y(R_m));

    // Master latch (NAND SR latch)
    wire Qm, Qm_bar;
    NAND2 mL1 (.A(S_m), .B(Qm_bar), .Y(Qm));
    NAND2 mL2 (.A(R_m), .B(Qm), .Y(Qm_bar));

    // Slave latch inputs (enabled when CLK = 1)
    wire S_s, R_s;
    NAND2 sS (.A(Qm), .B(CLK), .Y(S_s));
    NAND2 sR (.A(Qm_bar), .B(CLK), .Y(R_s));

    // Slave latch (NAND SR latch) -> outputs Q and QN
    wire Q_bar;
    NAND2 sL1 (.A(S_s), .B(Q_bar), .Y(Q));
    NAND2 sL2 (.A(R_s), .B(Q), .Y(Q_bar));

    // Provide complementary output
    assign QN = Q_bar;

endmodule

verilog/master_slave_D_FF/tb_master_slave_D_FF.v
`timescale 1ns/1ps
module tb_master_slave_D_FF;
    reg D;
    reg CLK;
    wire Q, QN;

    master_slave_D_FF uut(.D(D), .CLK(CLK), .Q(Q), .QN(QN));

    // Clock generator
    initial begin
        CLK = 0;
    end
    always #5 CLK = ~CLK; // 10ns period

    integer i;
    reg expected;

    initial begin
        $dumpfile("D_FF.vcd");
        $dumpvars(0, tb_master_slave_D_FF);

        D = 0;
        #3; // small offset so D changes on negedge below

        // Change D on negedge to ensure stable at posedge
        for (i = 0; i < 20; i = i + 1) begin
            @(negedge CLK);
            D = $random & 1;
        end

        #100 $finish;
    end

    // Check Q shortly after posedge (allow propagation)
    always @(posedge CLK) begin
        #1; // allow propagation through NAND network
        expected = D; // D at posedge (stable because we change on negedge)
        if (Q !== expected) begin
            $display("Mismatch at time %0t: D=%b Q=%b", $time, D, Q);
        end else begin
            $display("Match at time %0t: D=%b Q=%b", $time, D, Q);
        end
    end
endmodule

verilog/master_slave_D_FF/D_FF.vcd
$date
	Wed Dec  3 17:30:33 2025
$end
$version
	Icarus Verilog
$end
$timescale
	1ps
$end
$scope module tb_master_slave_D_FF $end
$var wire 1 ! QN $end
$var wire 1 " Q $end
$var reg 1 # CLK $end
$var reg 1 $ D $end
$var reg 1 % expected $end
$var integer 32 & i [31:0] $end
$scope module uut $end
$var wire 1 # CLK $end
$var wire 1 $ D $end
$var wire 1 ! QN $end
$var wire 1 ' nD $end
$var wire 1 ( nCLK $end
$var wire 1 ) S_s $end
$var wire 1 * S_m $end
$var wire 1 + R_s $end
$var wire 1 , R_m $end
$var wire 1 - Qm_bar $end
$var wire 1 . Qm $end
$var wire 1 / Q_bar $end
$var wire 1 " Q $end
$scope module invCLK $end
$var wire 1 # A $end
$var wire 1 # B $end
$var wire 1 ( Y $end
$upscope $end
$scope module invD $end
$var wire 1 $ A $end
$var wire 1 $ B $end
$var wire 1 ' Y $end
$upscope $end
$scope module mL1 $end
$var wire 1 . Y $end
$var wire 1 - B $end
$var wire 1 * A $end
$upscope $end
$scope module mL2 $end
$var wire 1 . B $end
$var wire 1 - Y $end
$var wire 1 , A $end
$upscope $end
$scope module mR $end
$var wire 1 ' A $end
$var wire 1 ( B $end
$var wire 1 , Y $end
$upscope $end
$scope module mS $end
$var wire 1 $ A $end
$var wire 1 ( B $end
$var wire 1 * Y $end
$upscope $end
$scope module sL1 $end
$var wire 1 " Y $end
$var wire 1 / B $end
$var wire 1 ) A $end
$upscope $end
$scope module sL2 $end
$var wire 1 " B $end
$var wire 1 / Y $end
$var wire 1 + A $end
$upscope $end
$scope module sR $end
$var wire 1 - A $end
$var wire 1 # B $end
$var wire 1 + Y $end
$upscope $end
$scope module sS $end
$var wire 1 . A $end
$var wire 1 # B $end
$var wire 1 ) Y $end
$upscope $end
$upscope $end
$upscope $end
$enddefinitions $end
$comment Show the parameter values. $end
$dumpall
$end
#0
$dumpvars
x/
0.
1-
0,
1+
1*
1)
1(
1'
bx &
x%
0$
0#
x"
x!
$end
#3000
b0 &
#5000
0"
1,
1!
1/
0(
0+
1#
#6000
0%
#10000
0,
1(
1+
b1 &
0#
#15000
1,
0(
0+
1#
#20000
0-
1.
0*
0'
1(
1+
b10 &
1$
0#
#25000
0!
0/
1*
1"
0(
0)
1#
#26000
1%
#30000
0*
1(
1)
b11 &
0#
#35000
1*
0(
0)
1#
#40000
0*
1(
1)
b100 &
0#
#45000
1*
0(
0)
1#
#50000
0*
1(
1)
b101 &
0#
#55000
1*
0(
0)
1#
#60000
0*
1(
1)
b110 &
0#
#65000
1*
0(
0)
1#
#70000
0*
1(
1)
b111 &
0#
#75000
1*
0(
0)
1#
#80000
0.
1-
0,
1'
1(
1)
b1000 &
0$
0#
#85000
0"
1,
1!
1/
0(
0+
1#
#86000
0%
#90000
0-
1.
0*
0'
1(
1+
b1001 &
1$
0#
#95000
0!
0/
1*
1"
0(
0)
1#
#96000
1%
#100000
0*
1(
1)
b1010 &
0#
#105000
1*
0(
0)
1#
#110000
0.
1-
0,
1'
1(
1)
b1011 &
0$
0#
#115000
0"
1,
1!
1/
0(
0+
1#
#116000
0%
#120000
0-
1.
0*
0'
1(
1+
b1100 &
1$
0#
#125000
0!
0/
1*
1"
0(
0)
1#
#126000
1%
#130000
0*
1(
1)
b1101 &
0#
#135000
1*
0(
0)
1#
#140000
0.
1-
0,
1'
1(
1)
b1110 &
0$
0#
#145000
0"
1,
1!
1/
0(
0+
1#
#146000
0%
#150000
0-
1.
0*
0'
1(
1+
b1111 &
1$
0#
#155000
0!
0/
1*
1"
0(
0)
1#
#156000
1%
#160000
0.
1-
0,
1'
1(
1)
b10000 &
0$
0#
#165000
0"
1,
1!
1/
0(
0+
1#
#166000
0%
#170000
0-
1.
0*
0'
1(
1+
b10001 &
1$
0#
#175000
0!
0/
1*
1"
0(
0)
1#
#176000
1%
#180000
0.
1-
0,
1'
1(
1)
b10010 &
0$
0#
#185000
0"
1,
1!
1/
0(
0+
1#
#186000
0%
#190000
0-
1.
0*
0'
1(
1+
b10011 &
1$
0#
#195000
0!
0/
1*
1"
0(
0)
1#
#196000
1%
#200000
0*
1(
1)
b10100 &
0#
#205000
1*
0(
0)
1#
#210000
0*
1(
1)
0#
#215000
1*
0(
0)
1#
#220000
0*
1(
1)
0#
#225000
1*
0(
0)
1#
#230000
0*
1(
1)
0#
#235000
1*
0(
0)
1#
#240000
0*
1(
1)
0#
#245000
1*
0(
0)
1#
#250000
0*
1(
1)
0#
#255000
1*
0(
0)
1#
#260000
0*
1(
1)
0#
#265000
1*
0(
0)
1#
#270000
0*
1(
1)
0#
#275000
1*
0(
0)
1#
#280000
0*
1(
1)
0#
#285000
1*
0(
0)
1#
#290000
0*
1(
1)
0#
#295000
1*
0(
0)
1#
#300000
0*
1(
1)
0#
