verilog/AND6/AND6.v
module AND6(input A, input B, input C, input D, input E, input F, output Y);
    assign Y = A & B & C & D & E & F;
endmodule

verilog/AND6/tb_AND6.v
`timescale 1ns/1ps
module tb_AND6;
    reg A, B, C, D, E, F;
    wire Y;
    integer i;

    AND6 uut(.A(A), .B(B), .C(C), .D(D), .E(E), .F(F), .Y(Y));

    initial begin
        $dumpfile("and6.vcd");
        $dumpvars(0, tb_AND6);

        for (i = 0; i < 64; i = i + 1) begin
            {A, B, C, D, E, F} = i;
            #10;
        end

        #20 $finish;
    end
endmodule

verilog/AND6/and6.vcd
$date
	Wed Dec  3 17:15:14 2025
$end
$version
	Icarus Verilog
$end
$timescale
	1ps
$end
$scope module tb_AND6 $end
$var wire 1 ! Y $end
$var reg 1 " A $end
$var reg 1 # B $end
$var reg 1 $ C $end
$var reg 1 % D $end
$var reg 1 & E $end
$var reg 1 ' F $end
$var integer 32 ( i [31:0] $end
$scope module uut $end
$var wire 1 " A $end
$var wire 1 # B $end
$var wire 1 $ C $end
$var wire 1 % D $end
$var wire 1 & E $end
$var wire 1 ' F $end
$var wire 1 ! Y $end
$upscope $end
$upscope $end
$enddefinitions $end
$comment Show the parameter values. $end
$dumpall
$end
#0
$dumpvars
b0 (
0'
0&
0%
0$
0#
0"
0!
$end
#10000
1'
b1 (
#20000
1&
0'
b10 (
#30000
1'
b11 (
#40000
1%
0&
0'
b100 (
#50000
1'
b101 (
#60000
1&
0'
b110 (
#70000
1'
b111 (
#80000
1$
0%
0&
0'
b1000 (
#90000
1'
b1001 (
#100000
1&
0'
b1010 (
#110000
1'
b1011 (
#120000
1%
0&
0'
b1100 (
#130000
1'
b1101 (
#140000
1&
0'
b1110 (
#150000
1'
b1111 (
#160000
1#
0$
0%
0&
0'
b10000 (
#170000
1'
b10001 (
#180000
1&
0'
b10010 (
#190000
1'
b10011 (
#200000
1%
0&
0'
b10100 (
#210000
1'
b10101 (
#220000
1&
0'
b10110 (
#230000
1'
b10111 (
#240000
1$
0%
0&
0'
b11000 (
#250000
1'
b11001 (
#260000
1&
0'
b11010 (
#270000
1'
b11011 (
#280000
1%
0&
0'
b11100 (
#290000
1'
b11101 (
#300000
1&
0'
b11110 (
#310000
1'
b11111 (
#320000
1"
0#
0$
0%
0&
0'
b100000 (
#330000
1'
b100001 (
#340000
1&
0'
b100010 (
#350000
1'
b100011 (
#360000
1%
0&
0'
b100100 (
#370000
1'
b100101 (
#380000
1&
0'
b100110 (
#390000
1'
b100111 (
#400000
1$
0%
0&
0'
b101000 (
#410000
1'
b101001 (
#420000
1&
0'
b101010 (
#430000
1'
b101011 (
#440000
1%
0&
0'
b101100 (
#450000
1'
b101101 (
#460000
1&
0'
b101110 (
#470000
1'
b101111 (
#480000
1#
0$
0%
0&
0'
b110000 (
#490000
1'
b110001 (
#500000
1&
0'
b110010 (
#510000
1'
b110011 (
#520000
1%
0&
0'
b110100 (
#530000
1'
b110101 (
#540000
1&
0'
b110110 (
#550000
1'
b110111 (
#560000
1$
0%
0&
0'
b111000 (
#570000
1'
b111001 (
#580000
1&
0'
b111010 (
#590000
1'
b111011 (
#600000
1%
0&
0'
b111100 (
#610000
1'
b111101 (
#620000
1&
0'
b111110 (
#630000
1!
1'
b111111 (
#640000
b1000000 (
