verilog/AND5/AND5.v
module AND5(input A, input B, input C, input D, input E, output Y);
    assign Y = A & B & C & D & E;
endmodule

verilog/AND5/tb_AND5.v
`timescale 1ns/1ps
module tb_AND5;
    reg A, B, C, D, E;
    wire Y;
    integer i;

    AND5 uut(.A(A), .B(B), .C(C), .D(D), .E(E), .Y(Y));

    initial begin
        $dumpfile("and5.vcd");
        $dumpvars(0, tb_AND5);

        for (i = 0; i < 32; i = i + 1) begin
            {A, B, C, D, E} = i;
            #10;
        end

        #20 $finish;
    end
endmodule

verilog/AND5/and5.vcd
$date
	Wed Dec  3 17:15:09 2025
$end
$version
	Icarus Verilog
$end
$timescale
	1ps
$end
$scope module tb_AND5 $end
$var wire 1 ! Y $end
$var reg 1 " A $end
$var reg 1 # B $end
$var reg 1 $ C $end
$var reg 1 % D $end
$var reg 1 & E $end
$var integer 32 ' i [31:0] $end
$scope module uut $end
$var wire 1 " A $end
$var wire 1 # B $end
$var wire 1 $ C $end
$var wire 1 % D $end
$var wire 1 & E $end
$var wire 1 ! Y $end
$upscope $end
$upscope $end
$enddefinitions $end
$comment Show the parameter values. $end
$dumpall
$end
#0
$dumpvars
b0 '
0&
0%
0$
0#
0"
0!
$end
#10000
1&
b1 '
#20000
1%
0&
b10 '
#30000
1&
b11 '
#40000
1$
0%
0&
b100 '
#50000
1&
b101 '
#60000
1%
0&
b110 '
#70000
1&
b111 '
#80000
1#
0$
0%
0&
b1000 '
#90000
1&
b1001 '
#100000
1%
0&
b1010 '
#110000
1&
b1011 '
#120000
1$
0%
0&
b1100 '
#130000
1&
b1101 '
#140000
1%
0&
b1110 '
#150000
1&
b1111 '
#160000
1"
0#
0$
0%
0&
b10000 '
#170000
1&
b10001 '
#180000
1%
0&
b10010 '
#190000
1&
b10011 '
#200000
1$
0%
0&
b10100 '
#210000
1&
b10101 '
#220000
1%
0&
b10110 '
#230000
1&
b10111 '
#240000
1#
0$
0%
0&
b11000 '
#250000
1&
b11001 '
#260000
1%
0&
b11010 '
#270000
1&
b11011 '
#280000
1$
0%
0&
b11100 '
#290000
1&
b11101 '
#300000
1%
0&
b11110 '
#310000
1!
1&
b11111 '
#320000
b100000 '
